beautifulsoup4_helpers/__init__.py
beautifulsoup4_helpers-0.0.1.dist-info/LICENSE
beautifulsoup4_helpers-0.0.1.dist-info/METADATA
beautifulsoup4_helpers-0.0.1.dist-info/WHEEL
beautifulsoup4_helpers-0.0.1.dist-info/top_level.txt
beautifulsoup4_helpers-0.0.1.dist-info/RECORD
