Metadata-Version: 2.1
Name: beautifulsoup4-helpers
Version: 0.0.1
Summary: Frequently used functions for html parsing with beautifulsoup4 https://pypi.org/project/beautifulsoup4/
Home-page: https://github.com/eugen1j/beautifulsoup4-helpers
Author: eugen1j
Author-email: eugenij.bondar@gmail.com
License: MIT
Keywords: python3
Platform: UNKNOWN
Classifier: License :: OSI Approved :: MIT License
Classifier: Programming Language :: Python
Classifier: Programming Language :: Python :: 3.7
Classifier: Development Status :: 3 - Alpha
Classifier: Operating System :: Unix
Classifier: Operating System :: Microsoft :: Windows
Classifier: Operating System :: MacOS
Requires-Python: >=3.7.0
Requires-Dist: beautifulsoup4
